airsim/__init__.py
airsim/client.py
airsim/control.py
airsim/exploration.py
airsim/pfm.py
airsim/timing.py
airsim/types.py
airsim/utils.py
mrl_airsim-0.0.4.dist-info/LICENSE
mrl_airsim-0.0.4.dist-info/METADATA
mrl_airsim-0.0.4.dist-info/WHEEL
mrl_airsim-0.0.4.dist-info/top_level.txt
mrl_airsim-0.0.4.dist-info/RECORD
