Metadata-Version: 2.1
Name: mrl-airsim
Version: 0.0.4
Summary: Fork of AirSim developped by McGill MRL (Mobile Robotics Lab). Original credit goes to Microsoft AI & Research for development of the AirSim package.
Home-page: https://github.com/microsoft/airsim
Author: Stefan Wapnick
Author-email: stefan.wapnick@mail.mcgill.ca
License: MIT
Platform: UNKNOWN
Classifier: Programming Language :: Python :: 3
Classifier: License :: OSI Approved :: MIT License
Classifier: Operating System :: OS Independent
Requires-Dist: msgpack-rpc-python
Requires-Dist: numpy
Requires-Dist: opencv-contrib-python
